README.md
setup.py
envirophat_mqtt/__init__.py
envirophat_mqtt/__main__.py
envirophat_mqtt.egg-info/PKG-INFO
envirophat_mqtt.egg-info/SOURCES.txt
envirophat_mqtt.egg-info/dependency_links.txt
envirophat_mqtt.egg-info/entry_points.txt
envirophat_mqtt.egg-info/requires.txt
envirophat_mqtt.egg-info/top_level.txt