Metadata-Version: 2.1
Name: envirophat-mqtt
Version: 1.1
Summary: Feed data from a pimoroni envirophat into mqtt
Home-page: https://github.com/garbled1/envirophat_mqtt
Author: Tim Rightnour
Author-email: the@garbled.one
License: Apache 2.0
Project-URL: Gitub Repo, https://github.com/garbled1/envirophat_mqtt
Platform: UNKNOWN
Requires-Python: >3.5
